CloudFlare_EOF/__init__.py
CloudFlare_EOF/main.py
CloudFlare_EOF-0.1.3.dist-info/LICENSE
CloudFlare_EOF-0.1.3.dist-info/METADATA
CloudFlare_EOF-0.1.3.dist-info/WHEEL
CloudFlare_EOF-0.1.3.dist-info/top_level.txt
CloudFlare_EOF-0.1.3.dist-info/RECORD
