Metadata-Version: 2.1
Name: CloudFlare_EOF
Version: 0.1.3
Summary: CloudFlare_EOF is a project to decode email addresses protected and Obfuscated by Cloudflare.
Home-page: https://github.com/Elxss/CloudFlare-Email-Obfuscation-Fucker
Author: Elxss
Author-email: elxssgitcontact@gmail.com
License-File: LICENSE
Requires-Dist: beautifulsoup4
